[{"id":0.14437505244497784,"houseName":"anuj's house","size":"7","location":"danapur","price":"10000","image":"https://wallpapercave.com/wp/wp2464233.jpg","description":"best property in danapur","favourite":false},{"id":"0.10533010505793095","houseName":"johnny's house","size":"10","location":"california","price":"10000","image":"https://tse3.mm.bing.net/th/id/OIP.B9ZqEM4lmehXjP-CRobIMwHaE8?rs=1&pid=ImgDetMain&o=7&rm=3","description":"best property in california","favourite":true},{"id":0.06483014337939519,"houseName":"mia khalifa's house","size":"7","location":"dubai","price":"10000","image":"https://images.pexels.com/photos/187815/pexels-photo-187815.jpeg","description":"best property in Dubai","favourite":true}]